fsrs_rs_python-0.8.2.dist-info/METADATA
fsrs_rs_python-0.8.2.dist-info/WHEEL
fsrs_rs_python/__init__.py
fsrs_rs_python/__init__.pyi
fsrs_rs_python/fsrs_rs_python.cpython-310-arm-linux-gnueabihf.so
fsrs_rs_python/py.typed
fsrs_rs_python-0.8.2.dist-info/RECORD
